argcmdr.py
argcmdr-1.1.0.dist-info/LICENSE
argcmdr-1.1.0.dist-info/METADATA
argcmdr-1.1.0.dist-info/WHEEL
argcmdr-1.1.0.dist-info/entry_points.txt
argcmdr-1.1.0.dist-info/top_level.txt
argcmdr-1.1.0.dist-info/RECORD
