Metadata-Version: 2.1
Name: argcmdr
Version: 1.1.0
Summary: Thin argparse wrapper for quick, clear and easy declaration of hierarchical console command interfaces
Home-page: https://github.com/dssg/argcmdr
Author: Center for Data Science and Public Policy
Author-email: datascifellows@gmail.com
License: MIT
Platform: UNKNOWN
Classifier: Development Status :: 4 - Beta
Classifier: Intended Audience :: Developers
Classifier: Natural Language :: English
Classifier: Programming Language :: Python :: 3
Classifier: Programming Language :: Python :: 3.6
Classifier: Programming Language :: Python :: 3.7
Classifier: Programming Language :: Python :: 3.8
Classifier: Programming Language :: Python :: 3.9
Classifier: Programming Language :: Python :: 3.10
Requires-Python: >=3.6
Requires-Dist: argcomplete (<3,>=1.9.4)
Requires-Dist: Dickens (~=2.0)
Requires-Dist: plumbum (~=1.8.1)
